autoclean_eeg2source/__init__.py
autoclean_eeg2source/cli.py
autoclean_eeg2source/example.py
autoclean_eeg2source/core/__init__.py
autoclean_eeg2source/core/continuous_processor.py
autoclean_eeg2source/core/converter.py
autoclean_eeg2source/core/gpu_processor.py
autoclean_eeg2source/core/memory_manager.py
autoclean_eeg2source/core/optimized_memory.py
autoclean_eeg2source/core/parallel_processor.py
autoclean_eeg2source/core/robust_processor.py
autoclean_eeg2source/io/__init__.py
autoclean_eeg2source/io/data_quality.py
autoclean_eeg2source/io/eeglab_reader.py
autoclean_eeg2source/io/exceptions.py
autoclean_eeg2source/io/validators.py
autoclean_eeg2source/utils/__init__.py
autoclean_eeg2source/utils/benchmarking.py
autoclean_eeg2source/utils/error_reporter.py
autoclean_eeg2source/utils/logging.py
autoclean_eeg2source-0.3.7.dist-info/licenses/LICENSE
autoclean_eeg2source-0.3.7.dist-info/METADATA
autoclean_eeg2source-0.3.7.dist-info/WHEEL
autoclean_eeg2source-0.3.7.dist-info/entry_points.txt
autoclean_eeg2source-0.3.7.dist-info/top_level.txt
autoclean_eeg2source-0.3.7.dist-info/RECORD
