Metadata-Version: 2.4
Name: autoclean-eeg2source
Version: 0.3.7
Summary: EEG source localization with DK atlas regions
Author-email: AutoClean Team <ernest.pedapati@cchmc.org>
License-Expression: MIT
Classifier: Development Status :: 3 - Alpha
Classifier: Intended Audience :: Science/Research
Classifier: Topic :: Scientific/Engineering :: Medical Science Apps.
Classifier: Programming Language :: Python :: 3
Classifier: Programming Language :: Python :: 3.10
Classifier: Programming Language :: Python :: 3.11
Classifier: Programming Language :: Python :: 3.12
Requires-Python: <3.13,>=3.9
License-File: LICENSE
Requires-Dist: mne
Requires-Dist: numpy>1.24.4
Requires-Dist: pandas
Requires-Dist: loguru
Requires-Dist: psutil
Requires-Dist: nibabel
Requires-Dist: eeglabio
Requires-Dist: joblib
Provides-Extra: dev
Requires-Dist: pytest>=6.0; extra == "dev"
Requires-Dist: pytest-cov; extra == "dev"
Requires-Dist: build; extra == "dev"
Requires-Dist: twine; extra == "dev"
Dynamic: license-file
